hangeul_jamo_py/__init__.py
hangeul_jamo_py/constants.py
hangeul_jamo_py/core.py
hangeul_jamo_py/py.typed
hangeul_jamo_py-1.0.0.dist-info/WHEEL
hangeul_jamo_py-1.0.0.dist-info/METADATA
hangeul_jamo_py-1.0.0.dist-info/RECORD
