Metadata-Version: 2.3
Name: hangeul-jamo-py
Version: 1.0.0
Summary: A modern, optimized Korean Hangul syllable and jamo manipulation library
Keywords: korean,hangul,jamo,nlp,korean-language
Author: gembleman
Author-email: gembleman <81058727+gembleman@users.noreply.github.com>
Classifier: Development Status :: 5 - Production/Stable
Classifier: Intended Audience :: Developers
Classifier: License :: OSI Approved :: MIT License
Classifier: Programming Language :: Python :: 3
Classifier: Programming Language :: Python :: 3.13
Classifier: Topic :: Text Processing :: Linguistic
Classifier: Typing :: Typed
Requires-Python: >=3.13
Project-URL: Documentation, https://github.com/gembleman/hangeul_jamo
Project-URL: Homepage, https://github.com/gembleman/hangeul_jamo
Project-URL: Repository, https://github.com/gembleman/hangeul_jamo
